[
  {
    "@type": "ScreeningEvent",
    "name": "Lepes(2025)",
    "url": "https://fillum.in/screening/5021",
    "startDate": "2026-03-16T14:00:00+05:30",
    "endDate": "2026-03-16T14:00:00+05:30",
    "description": "Free entry.",
    "location": {
      "@type": "Place",
      "name": "Stein Auditorium, India Habitat Centre",
      "address": "Delhi"
    },
    "organizer": {
      "@type": "Organization",
      "name": "Habitat International Film Festival"
    }
  },
  {
    "@type": "ScreeningEvent",
    "name": "The Promised Land(1975)",
    "url": "https://fillum.in/screening/5022",
    "startDate": "2026-03-16T14:00:00+05:30",
    "endDate": "2026-03-16T14:00:00+05:30",
    "description": "Free entry.",
    "location": {
      "@type": "Place",
      "name": "The Theatre, India Habitat Centre",
      "address": "Delhi"
    },
    "organizer": {
      "@type": "Organization",
      "name": "Habitat International Film Festival"
    }
  },
  {
    "@type": "ScreeningEvent",
    "name": "Birthright(2025)",
    "url": "https://fillum.in/screening/5023",
    "startDate": "2026-03-16T16:00:00+05:30",
    "endDate": "2026-03-16T16:00:00+05:30",
    "description": "Free entry.",
    "location": {
      "@type": "Place",
      "name": "Stein Auditorium, India Habitat Centre",
      "address": "Delhi"
    },
    "organizer": {
      "@type": "Organization",
      "name": "Habitat International Film Festival"
    }
  },
  {
    "@type": "ScreeningEvent",
    "name": "Sound of Falling(2025)",
    "url": "https://fillum.in/screening/5024",
    "startDate": "2026-03-16T18:00:00+05:30",
    "endDate": "2026-03-16T18:00:00+05:30",
    "description": "Free entry.",
    "location": {
      "@type": "Place",
      "name": "Stein Auditorium, India Habitat Centre",
      "address": "Delhi"
    },
    "organizer": {
      "@type": "Organization",
      "name": "Habitat International Film Festival"
    }
  },
  {
    "@type": "ScreeningEvent",
    "name": "Hungarians(1978)",
    "url": "https://fillum.in/screening/5025",
    "startDate": "2026-03-16T18:30:00+05:30",
    "endDate": "2026-03-16T18:30:00+05:30",
    "description": "Free entry.",
    "location": {
      "@type": "Place",
      "name": "The Theatre, India Habitat Centre",
      "address": "Delhi"
    },
    "organizer": {
      "@type": "Organization",
      "name": "Habitat International Film Festival"
    }
  },
  {
    "@type": "ScreeningEvent",
    "name": "Pelikan Blue(2024)",
    "url": "https://fillum.in/screening/5026",
    "startDate": "2026-03-16T21:00:00+05:30",
    "endDate": "2026-03-16T21:00:00+05:30",
    "description": "Free entry.",
    "location": {
      "@type": "Place",
      "name": "Stein Auditorium, India Habitat Centre",
      "address": "Delhi"
    },
    "organizer": {
      "@type": "Organization",
      "name": "Habitat International Film Festival"
    }
  },
  {
    "@type": "ScreeningEvent",
    "name": "Unlimited Girls(2002)",
    "url": "https://fillum.in/screening/5129",
    "startDate": "2026-03-17T11:10:00+05:30",
    "endDate": "2026-03-17T11:10:00+05:30",
    "description": "As part of our Feminist Film Festival, organized by SFI DU.",
    "location": {
      "@type": "Place",
      "name": "HKS Bhawan, ITO",
      "address": "Delhi"
    },
    "organizer": {
      "@type": "Organization",
      "name": "SFI Delhi University"
    }
  },
  {
    "@type": "ScreeningEvent",
    "name": "Voh Subah Hami Se Aayegi(2025)",
    "url": "https://fillum.in/screening/5130",
    "startDate": "2026-03-17T13:15:00+05:30",
    "endDate": "2026-03-17T13:15:00+05:30",
    "description": "As part of our Feminist Film Festival, organized by SFI DU.",
    "location": {
      "@type": "Place",
      "name": "HKS Bhawan, ITO",
      "address": "Delhi"
    },
    "organizer": {
      "@type": "Organization",
      "name": "SFI Delhi University"
    }
  },
  {
    "@type": "ScreeningEvent",
    "name": "The Currents(2026)",
    "url": "https://fillum.in/screening/5027",
    "startDate": "2026-03-17T14:00:00+05:30",
    "endDate": "2026-03-17T14:00:00+05:30",
    "description": "Free entry.",
    "location": {
      "@type": "Place",
      "name": "Stein Auditorium, India Habitat Centre",
      "address": "Delhi"
    },
    "organizer": {
      "@type": "Organization",
      "name": "Habitat International Film Festival"
    }
  },
  {
    "@type": "ScreeningEvent",
    "name": "Man of Marble(1977)",
    "url": "https://fillum.in/screening/5029",
    "startDate": "2026-03-17T14:00:00+05:30",
    "endDate": "2026-03-17T14:00:00+05:30",
    "description": "Free entry.",
    "location": {
      "@type": "Place",
      "name": "The Theatre, India Habitat Centre",
      "address": "Delhi"
    },
    "organizer": {
      "@type": "Organization",
      "name": "Habitat International Film Festival"
    }
  }
]