[
  {
    "@type": "ScreeningEvent",
    "name": "I Saw the Devil(2010)",
    "url": "https://fillum.in/screening/5397",
    "startDate": "2026-05-09T14:30:00+05:30",
    "endDate": "2026-05-09T14:30:00+05:30",
    "description": "",
    "location": {
      "@type": "Place",
      "name": "Niv Art Centre, Saket",
      "address": "Sainik Farm, New Delhi"
    },
    "organizer": {
      "@type": "Organization",
      "name": "Delhi Screen Society"
    }
  },
  {
    "@type": "ScreeningEvent",
    "name": "A Tale of Two Sisters(2003)",
    "url": "https://fillum.in/screening/5395",
    "startDate": "2026-05-09T17:30:00+05:30",
    "endDate": "2026-05-09T17:30:00+05:30",
    "description": "",
    "location": {
      "@type": "Place",
      "name": "Niv Art Centre, Saket",
      "address": "Sainik Farm, New Delhi"
    },
    "organizer": {
      "@type": "Organization",
      "name": "Delhi Screen Society"
    }
  },
  {
    "@type": "ScreeningEvent",
    "name": "Bulbul(2026)",
    "url": "https://fillum.in/screening/5468",
    "startDate": "2026-05-09T19:30:00+05:30",
    "endDate": "2026-05-09T19:30:00+05:30",
    "description": "Free entry.",
    "location": {
      "@type": "Place",
      "name": "Niv Art Centre, Neb Sarai",
      "address": "Sainik Farm, New Delhi"
    },
    "organizer": {
      "@type": "Organization",
      "name": "Fillum"
    }
  },
  {
    "@type": "ScreeningEvent",
    "name": "Burning(2018)",
    "url": "https://fillum.in/screening/5398",
    "startDate": "2026-05-10T12:00:00+05:30",
    "endDate": "2026-05-10T12:00:00+05:30",
    "description": "",
    "location": {
      "@type": "Place",
      "name": "Niv Art Centre, Saket",
      "address": "Sainik Farm, New Delhi"
    },
    "organizer": {
      "@type": "Organization",
      "name": "Delhi Screen Society"
    }
  }
]